.travis.yml
README.rst
bootstrap.py
buildout.cfg
setup.py
test-4.0.x.cfg
test-4.1.x.cfg
test-4.2.x.cfg
test-4.3.x.cfg
.tx/config
collective/__init__.py
collective.portlet.ngcollection.egg-info/PKG-INFO
collective.portlet.ngcollection.egg-info/SOURCES.txt
collective.portlet.ngcollection.egg-info/dependency_links.txt
collective.portlet.ngcollection.egg-info/entry_points.txt
collective.portlet.ngcollection.egg-info/namespace_packages.txt
collective.portlet.ngcollection.egg-info/not-zip-safe
collective.portlet.ngcollection.egg-info/requires.txt
collective.portlet.ngcollection.egg-info/top_level.txt
collective/portlet/__init__.py
collective/portlet/ngcollection/TODO.txt
collective/portlet/ngcollection/__init__.py
collective/portlet/ngcollection/configure.zcml
collective/portlet/ngcollection/interfaces.py
collective/portlet/ngcollection/manager.py
collective/portlet/ngcollection/meta.zcml
collective/portlet/ngcollection/metaconfigure.py
collective/portlet/ngcollection/metadirectives.py
collective/portlet/ngcollection/migration.py
collective/portlet/ngcollection/ngcollection.pt
collective/portlet/ngcollection/ngcollection.py
collective/portlet/ngcollection/vocabularies.py
collective/portlet/ngcollection/locales/collective.portlet.ngcollection.pot
collective/portlet/ngcollection/locales/da/LC_MESSAGES/collective.portlet.ngcollection.po
collective/portlet/ngcollection/locales/fr/LC_MESSAGES/collective.portlet.ngcollection.po
collective/portlet/ngcollection/locales/uk/LC_MESSAGES/collective.portlet.ngcollection.po
collective/portlet/ngcollection/profiles/default/metadata.xml
collective/portlet/ngcollection/profiles/default/portlets.xml
collective/portlet/ngcollection/tests/__init__.py
collective/portlet/ngcollection/tests/base.py
collective/portlet/ngcollection/tests/test_portlet.py
collective/portlet/ngcollection/tests/templates/test.pt
docs/HISTORY.rst
docs/INSTALL.txt
docs/LICENSE.GPL
docs/LICENSE.txt