Metadata-Version: 1.1
Name: collective.portlet.ngcollection
Version: 1.4
Summary: Extends plone collection portlet in order to allow assigning different views for each newly created portlet through it's edit form
Home-page: https://github.com/collective/collective.portlet.ngcollection
Author: Quintagroup
Author-email: support@quintagroup.com
License: GPL
Keywords: plone portlet collection
Platform: UNKNOWN
Classifier: Environment :: Web Environment
Classifier: Framework :: Zope2
Classifier: Framework :: Plone
Classifier: Framework :: Plone :: 4.0
Classifier: Framework :: Plone :: 4.1
Classifier: Framework :: Plone :: 4.2
Classifier: Framework :: Plone :: 4.3
Classifier: Programming Language :: Python
Classifier: Development Status :: 5 - Production/Stable
Classifier: Intended Audience :: Developers
Classifier: Natural Language :: English
Classifier: Operating System :: OS Independent
Classifier: Topic :: Internet :: WWW/HTTP :: Dynamic Content
Classifier: Topic :: Software Development :: Libraries :: Python Modules
Classifier: License :: OSI Approved :: GNU General Public License (GPL)
